zksoap/__init__.py
zksoap/fingerprint.py
zksoap-0.0.6.dist-info/LICENSE
zksoap-0.0.6.dist-info/METADATA
zksoap-0.0.6.dist-info/WHEEL
zksoap-0.0.6.dist-info/top_level.txt
zksoap-0.0.6.dist-info/RECORD
