Metadata-Version: 2.1
Name: zksoap
Version: 0.0.6
Home-page: https://fahriztx.dev/
Author: Muhammad Fahri
Author-email: admin@fahriztx.dev
License: MIT
Project-URL: Bug Tracker, https://github.com/FAHRIZTX/ZKSoap-Python/issues
Project-URL: Documentation, https://github.com/FAHRIZTX/ZKSoap-Python/blob/master/README.md
Project-URL: Source Code, https://github.com/FAHRIZTX/ZKSoap-Python
Requires-Python: >=3.6
License-File: LICENSE
